{
  "mathe": [  
    {"a": "x^2 + x^2", "l": ["2x^2", "x^4", "x^8", "2x^4"]},
    {"a": "x^2 \\cdot x^2", "l": ["x^4", "x^2", "2x^2", "4x"]},
    {"a": "(x + 3)^2", "l": ["x^2 + 6x + 9", "x^2 + 3", "x^2 + 9", "x^2 + 3x + 9"]},
    {"a": "\\frac{d}{dx} x^3", "l": ["3x^2", "3x", "x^2", "x^3"]},
    {"a": "\\int 2x \\, dx", "l": ["x^2 + C", "2x + C", "x + C", "2x^2 + C"]},
    {"a": "x^2 = 9 , x=?", "l": ["±3", "3", "-3", "0"]},
    {"a": "\\sin(90°)", "l": ["1", "0", "-1", "0.5"]},
    {"a": "0!", "l": ["1", "0", "undefiniert", "-1"]},
    {"a": "\\frac{d}{dx} \\sin(x)", "l": ["\\cos(x)", "-\\sin(x)", "\\tan(x)", "1"]},
    {"a": "\\log_{10}(1000)", "l": ["3", "10", "100", "1"] }
  ],
  "it": [
    {"a": "Welche Authentifizierung bietet HTTP", "l": ["Digest Access Authentication", "OTP", "OAuth", "2-Faktor-Authentifizierung"]},
    {"a": "Welches Transportprotokoll eignet sich für zeitkritische Übertragungen", "l": ["UDP", "TCP", "HTTP", "Fast Retransmit"]},
    {"a": "Wofür steht HTML?", "l": ["HyperText Markup Language", "HyperTool Multi Language", "HighText Markup Language", "HyperText Management Language"]},
    {"a": "Was ist ein Vorteil von REST?", "l": ["Zustandslosigkeit", "Persistente Verbindungen", "Client-Zustandsverwaltung", "SOAP-Kompatibilität"]},
    {"a": "Was bedeutet 'responsive Design'?", "l": ["Anpassung an verschiedene Bildschirmgrößen", "Schnelle Ladezeit", "JavaScript-basierte Animation", "Server-Side Rendering"]},
    {"a": "Wofür steht CSS?", "l": ["Cascading Style Sheets", "Creative Style Syntax", "Computer Style Settings", "Cascading Script Sheets"]},
    {"a": "Was macht ein GET-Request?", "l": ["Fordert Daten vom Server an", "Sendet Daten an den Server", "Löscht Daten", "Aktualisiert Daten"]},
    {"a": "Was ist ein Cookie?", "l": ["Kleine Dateneinheit zur Speicherung im Browser", "Ein Serverprotokoll", "Ein Sicherheitstool", "Ein Netzwerkpaket"]},
    {"a": "Was ist ein CDN?", "l": ["Content Delivery Network", "Central Data Node", "Compressed Document Notation", "Code Deployment Namespace"]},
    {"a": "Was ist der Zweck von HTTPS?", "l": ["Verschlüsselte Datenübertragung", "Schnelleres Laden", "Caching", "Standardisierung von HTTP-Versionen"]}
  ],

  "allgemein": [
    {"a": "Karl der Große, Geburtsjahr", "l": ["747", "828", "650", "1150"]},
    {"a": "Hauptstadt von Kanada", "l": ["Ottawa", "Toronto", "Vancouver", "Montreal"]},
    {"a": "Größter Planet im Sonnensystem", "l": ["Jupiter", "Saturn", "Erde", "Neptun"]},
    {"a": "Wer malte die Mona Lisa?", "l": ["Leonardo da Vinci", "Michelangelo", "Raphael", "Van Gogh"]},
    {"a": "Wie viele Bundesländer hat Deutschland?", "l": ["16", "15", "14", "17"]},
    {"a": "Welcher Kontinent ist am kleinsten?", "l": ["Australien", "Europa", "Antarktis", "Afrika"]},
    {"a": "In welchem Jahr fiel die Berliner Mauer?", "l": ["1989", "1990", "1987", "1991"]},
    {"a": "Wie heißt die Hauptstadt von Spanien?", "l": ["Madrid", "Barcelona", "Sevilla", "Valencia"]},
    {"a": "Was ist die chemische Formel von Wasser?", "l": ["H2O", "O2", "CO2", "NaCl"]},
    {"a": "Welcher Planet ist der Sonne am nächsten?", "l": ["Merkur", "Venus", "Erde", "Mars"]}
  ],

  "noten": [
    { "a": "Welche Note ist das?::c/4", "l": ["c", "d", "e", "f"] },
    { "a": "Wie heißt diese Note?::f#/3", "l": ["f#", "f", "g", "e"] },
    { "a": "Erkenne die Note::d/5", "l": ["d", "e", "c", "a"] },
    { "a": "Welche Note ist hier notiert?::a/3", "l": ["a", "g", "b", "d"] },
    { "a": "Was ist das für eine Note?::e/4", "l": ["e", "f", "g", "d"] },
    { "a": "Tonart?::e/4;g/4;b/4", "l": ["E-Moll", "G-Dur", "C-Dur", "F-Dur"] },
    { "a": "Tonart?::c/4;e/4;g/4", "l": ["C-Dur", "A-Moll", "F-Dur", "G-Dur"] },
    { "a": "Tonart?::a/3;c/4;e/4", "l": ["A-Moll", "C-Dur", "E-Moll", "F-Dur"] },
    { "a": "Grundton?::d/4;f#/4;a/4", "l": ["d", "f#", "a", "g"] },
    { "a": "Akkordtyp?::g/3;b/3;d/4", "l": ["Dur", "Moll", "vermindert", "übermäßig"] }
  ],

  "akkorde": [
    { "a": "Tonart?::e/5,g#/5,b/5", "l": ["E-Dur", "C-Moll", "A-Dur", "G-Dur"] },
    { "a": "Grundton?::d/4,f#/4,a/4", "l": ["d", "f#", "a", "g"] },
    { "a": "Tonart?::f/4,a/4,c/5", "l": ["F-Dur", "D-Moll", "B-Dur", "C-Dur"] },
    { "a": "Grundton?::a/3,c/4,e/4", "l": ["a", "c", "e", "g"] },
    { "a": "Tonart?::g/3,b/3,d/4", "l": ["G-Dur", "E-Moll", "C-Dur", "D-Dur"] },
    { "a": "Grundton?::c/4,eb/4,g/4", "l": ["c", "eb", "g", "a"] },
    { "a": "Tonart?::bb/3,d#/4,f#/4", "l": ["B-Dur", "H-Dur", "G#-Moll", "F#-Dur"] },
    { "a": "Grundton?::b/3,d#/4,f#/4", "l": ["h", "f#", "d#", "g#"] },
    { "a": "Tonart?::c#/4,e/4,g#/4", "l": ["C#-Moll", "A-Dur", "C-Dur", "E-Moll"] },
    { "a": "Grundton?::f#/3,a/3,c#/4", "l": ["f#", "a", "c#", "e"] }
  ]
}
